ct_archived_tags/__init__.py
ct_archived_tags/comet.py
ct_archived_tags/comicbookinfo.py
ct_archived_tags-1.0.1.dist-info/LICENSE
ct_archived_tags-1.0.1.dist-info/METADATA
ct_archived_tags-1.0.1.dist-info/WHEEL
ct_archived_tags-1.0.1.dist-info/entry_points.txt
ct_archived_tags-1.0.1.dist-info/top_level.txt
ct_archived_tags-1.0.1.dist-info/RECORD
